{
	"info": {
		"_postman_id": "039d5e49-6917-4a3b-a018-95f57a05c124",
		"name": "JardelSilva-Avaliação1",
		"schema": "https://schema.getpostman.com/json/collection/v2.1.0/collection.json",
		"_exporter_id": "17572947"
	},
	"item": [
		{
			"name": "Salvar filme 2",
			"request": {
				"method": "POST",
				"header": [],
				"body": {
					"mode": "raw",
					"raw": "{\r\n      \"name\": \"Duro de Matar\",\r\n      \"genre\": \"Ação\",\r\n      \"urlStream\": \"http://jardelflix/acao/duro-de-matar\"\r\n}\r\n",
					"options": {
						"raw": {
							"language": "json"
						}
					}
				},
				"url": {
					"raw": "{{baseUrl}}/movies",
					"host": [
						"{{baseUrl}}"
					],
					"path": [
						"movies"
					]
				}
			},
			"response": []
		},
		{
			"name": "Buscar filme por genero em catalog-service",
			"request": {
				"method": "GET",
				"header": [],
				"url": {
					"raw": "{{baseUrl}}/catalog/ação",
					"host": [
						"{{baseUrl}}"
					],
					"path": [
						"catalog",
						"ação"
					]
				}
			},
			"response": []
		},
		{
			"name": "Salvar filme 1",
			"request": {
				"method": "POST",
				"header": [],
				"body": {
					"mode": "raw",
					"raw": "{\r\n      \"name\": \"Elysium\",\r\n      \"genre\": \"Ação\",\r\n      \"urlStream\": \"http://jardelflix/acao/elysium\"\r\n}",
					"options": {
						"raw": {
							"language": "json"
						}
					}
				},
				"url": {
					"raw": "{{baseUrl}}/movies",
					"host": [
						"{{baseUrl}}"
					],
					"path": [
						"movies"
					]
				}
			},
			"response": []
		},
		{
			"name": "Salvar filme 3",
			"request": {
				"method": "POST",
				"header": [],
				"body": {
					"mode": "raw",
					"raw": "{\r\n      \"name\": \"Missão Impossível\",\r\n      \"genre\": \"Ação\",\r\n      \"urlStream\": \"http://jardelflix/acao/missao-impossivel\"\r\n}",
					"options": {
						"raw": {
							"language": "json"
						}
					}
				},
				"url": {
					"raw": "{{baseUrl}}/movies",
					"host": [
						"{{baseUrl}}"
					],
					"path": [
						"movies"
					]
				}
			},
			"response": []
		}
	],
	"event": [
		{
			"listen": "prerequest",
			"script": {
				"type": "text/javascript",
				"exec": [
					""
				]
			}
		},
		{
			"listen": "test",
			"script": {
				"type": "text/javascript",
				"exec": [
					""
				]
			}
		}
	],
	"variable": [
		{
			"key": "baseUrl",
			"value": "http://localhost:8080",
			"type": "string"
		}
	]
}